ip_camera_record/__init__.py
ip_camera_record/ip_camera_record.py
ip_camera_record-0.0.11.dist-info/METADATA
ip_camera_record-0.0.11.dist-info/WHEEL
ip_camera_record-0.0.11.dist-info/entry_points.txt
ip_camera_record-0.0.11.dist-info/top_level.txt
ip_camera_record-0.0.11.dist-info/RECORD
